pycgapi/__init__.py
pycgapi/__version__.py
pycgapi/api.py
pycgapi/utils.py
pycgapi-0.1.4.dist-info/LICENSE
pycgapi-0.1.4.dist-info/METADATA
pycgapi-0.1.4.dist-info/WHEEL
pycgapi-0.1.4.dist-info/top_level.txt
pycgapi-0.1.4.dist-info/RECORD
