Metadata-Version: 2.1
Name: pycgapi
Version: 0.1.4
Summary: A Python wrapper for the CoinGecko API
Home-page: https://github.com/nathanramoscfa/pycgapi
Author: Nathan Ramos, CFA
Author-email: nathan.ramos.github@gmail.com
Classifier: Development Status :: 4 - Beta
Classifier: Intended Audience :: Developers
Classifier: Natural Language :: English
Classifier: Programming Language :: Python :: 3.9
Classifier: Programming Language :: Python :: 3.10
Classifier: Programming Language :: Python :: 3.11
Classifier: Operating System :: OS Independent
Classifier: Topic :: Software Development :: Libraries :: Python Modules
Classifier: Intended Audience :: Developers
Classifier: Intended Audience :: Financial and Insurance Industry
Classifier: License :: OSI Approved :: MIT License
Requires-Python: >=3.9, <3.12
License-File: LICENSE
Requires-Dist: coverage ~=7.4.0
Requires-Dist: flake8 ~=7.0.0
Requires-Dist: keyring ~=24.3.0
Requires-Dist: numpy ~=1.23.5
Requires-Dist: pandas ~=2.1.3
Requires-Dist: pytest-cov ~=4.1.0
Requires-Dist: pytz ~=2023.3
Requires-Dist: requests ~=2.31.0
Requires-Dist: sphinx ~=5.0.2
Requires-Dist: sphinx-rtd-theme ~=2.0.0
Requires-Dist: tqdm ~=4.66.1
Requires-Dist: urllib3 ~=2.1.0
